armcrop/__init__.py
armcrop/crops.py
armcrop/detect.py
armcrop/group.py
armcrop/model_manager.py
armcrop/segmentation_transform.py
armcrop-1.2.1.dist-info/METADATA
armcrop-1.2.1.dist-info/WHEEL
armcrop-1.2.1.dist-info/RECORD
