Metadata-Version: 2.3
Name: armcrop
Version: 1.2.1
Summary: A machine learning model that crops CT scans to a bone of interest in the arm
Author: Gregory Spangenberg
Author-email: gspangen@westerneng.ca
Requires-Python: >=3.11
Classifier: Programming Language :: Python :: 3
Classifier: Programming Language :: Python :: 3.11
Classifier: Programming Language :: Python :: 3.12
Classifier: Programming Language :: Python :: 3.13
Requires-Dist: huggingface-hub (>=0.25.1)
Requires-Dist: networkx (>=3.3)
Requires-Dist: numpy (==2.*)
Requires-Dist: onnxruntime (>=1.19)
Requires-Dist: opencv-python (>4)
Requires-Dist: pandas (>=2.2.3)
Requires-Dist: simpleitk (>=2.4.0)
Requires-Dist: simpleitkutilities (>=0.3.0,<0.4.0)
Requires-Dist: vtk (>=9.4.0)
